exa_py/__init__.py
exa_py/api.py
exa_py/py.typed
exa_py/utils.py
exa_py/research/__init__.py
exa_py/research/async_client.py
exa_py/research/base.py
exa_py/research/models.py
exa_py/research/sync_client.py
exa_py/research/utils.py
exa_py/websets/__init__.py
exa_py/websets/async_client.py
exa_py/websets/client.py
exa_py/websets/types.py
exa_py/websets/core/__init__.py
exa_py/websets/core/async_base.py
exa_py/websets/core/base.py
exa_py/websets/enrichments/__init__.py
exa_py/websets/enrichments/client.py
exa_py/websets/events/__init__.py
exa_py/websets/events/client.py
exa_py/websets/imports/__init__.py
exa_py/websets/imports/client.py
exa_py/websets/items/__init__.py
exa_py/websets/items/client.py
exa_py/websets/monitors/__init__.py
exa_py/websets/monitors/client.py
exa_py/websets/monitors/runs/__init__.py
exa_py/websets/monitors/runs/client.py
exa_py/websets/searches/__init__.py
exa_py/websets/searches/client.py
exa_py/websets/webhooks/__init__.py
exa_py/websets/webhooks/client.py
exa_py-2.0.2.dist-info/METADATA
exa_py-2.0.2.dist-info/WHEEL
exa_py-2.0.2.dist-info/top_level.txt
exa_py-2.0.2.dist-info/RECORD
