Metadata-Version: 2.1
Name: exa_py
Version: 2.0.2
Summary: Python SDK for Exa API.
Home-page: https://github.com/exa-labs/exa-py
Author: Exa
Author-email: hello@exa.ai
License: UNKNOWN
Platform: UNKNOWN
Classifier: Development Status :: 5 - Production/Stable
Classifier: Intended Audience :: Developers
Classifier: License :: OSI Approved :: MIT License
Classifier: Typing :: Typed
Classifier: Programming Language :: Python :: 3.8
Classifier: Programming Language :: Python :: 3.9
Classifier: Programming Language :: Python :: 3.10
Classifier: Programming Language :: Python :: 3.11
Classifier: Programming Language :: Python :: 3.12
